baelfire/__init__.py
baelfire/core.py
baelfire/error.py
baelfire/filedict.py
baelfire/parrented.py
baelfire/application/__init__.py
baelfire/application/application.py
baelfire/application/commands/__init__.py
baelfire/application/commands/graph/__init__.py
baelfire/application/commands/graph/graph.py
baelfire/application/commands/graph/models.py
baelfire/application/commands/graph/tests/__init__.py
baelfire/application/commands/graph/tests/test_graphs.py
baelfire/application/commands/graph/visualizators/__init__.py
baelfire/application/commands/graph/visualizators/chooser.py
baelfire/application/commands/graph/visualizators/dependency.py
baelfire/application/commands/graph/visualizators/link.py
baelfire/application/commands/graph/visualizators/task.py
baelfire/application/tests/__init__.py
baelfire/application/tests/test_application.py
baelfire/dependencies/__init__.py
baelfire/dependencies/dependency.py
baelfire/dependencies/file.py
baelfire/dependencies/pid.py
baelfire/dependencies/screen.py
baelfire/dependencies/task.py
baelfire/dependencies/tests/__init__.py
baelfire/dependencies/tests/test_core.py
baelfire/dependencies/tests/test_dependency.py
baelfire/dependencies/tests/test_file.py
baelfire/dependencies/tests/test_pid.py
baelfire/dependencies/tests/test_screen.py
baelfire/dependencies/tests/test_task.py
baelfire/task/__init__.py
baelfire/task/file.py
baelfire/task/process.py
baelfire/task/screen.py
baelfire/task/task.py
baelfire/task/template.py
baelfire/task/tests/__init__.py
baelfire/task/tests/test_core.py
baelfire/task/tests/test_file.py
baelfire/task/tests/test_proccess.py
baelfire/task/tests/test_screen.py
baelfire/task/tests/test_tasks.py
baelfire/task/tests/test_template.py
baelfire/tests/__init__.py
baelfire/tests/test_error.py
baelfire/tests/test_filedict.py
baelfire/tests/test_parrented.py
baelfire-0.5.1.dist-info/DESCRIPTION.rst
baelfire-0.5.1.dist-info/METADATA
baelfire-0.5.1.dist-info/RECORD
baelfire-0.5.1.dist-info/WHEEL
baelfire-0.5.1.dist-info/entry_points.txt
baelfire-0.5.1.dist-info/metadata.json
baelfire-0.5.1.dist-info/top_level.txt
tester/__init__.py
tester/data.py
tester/doc1.py
tester/taskme3.py
tester/tasks.py
tester/testme.py
