Metadata-Version: 2.0
Name: baelfire
Version: 0.5.1
Summary: Tool for build automatization and a task runner
Home-page: UNKNOWN
Author: Dominik "Socek" Długajczyk
Author-email: msocek@gmail.com
License: Apache License 2.0
Platform: UNKNOWN
Requires-Dist: jinja2
Requires-Dist: morfdict (>=0.4.1)
Requires-Dist: pyyaml
